{"cells":[{"type":"basic.Image","position":{"x":100,"y":100},"size":{"width":100,"height":100},"angle":0,"id":"1","z":1,"attrs":{"text":{"text":"Marketing","display":"","stroke":"#000000"},"image":{"xlink:href":"../../assets/Images/marketing.jpg","width":100,"height":100}}},{"type":"basic.Image","position":{"x":350,"y":100},"size":{"width":100,"height":100},"angle":0,"id":"2","z":2,"attrs":{"text":{"text":"Something","display":"","stroke":"#000000"},"image":{"xlink:href":"../../assets/Images/earth.jpg","width":100,"height":100}}},{"type":"standard.Link","source":{"id":"1","port":"out"},"target":{"id":"2","port":"in"},"id":"f0e73419-e8bf-4223-8bc0-dc6205e9b706","labels":[{"attrs":{"text":{"text":"Requires"}}}],"z":3,"attrs":{"line":{"stroke":"red"}}},{"type":"basic.Image","position":{"x":150,"y":350},"size":{"width":100,"height":100},"angle":0,"id":"3","z":4,"attrs":{"text":{"text":"Shopping cart","display":"","stroke":"#000000"},"image":{"xlink:href":"../../assets/Images/window.jpg","width":100,"height":100}}},{"type":"standard.Link","source":{"id":"2","port":"out"},"target":{"id":"3","port":"in"},"id":"593e4983-0686-4fe4-b596-c4e944d143c6","labels":[{"attrs":{"text":{"text":"Requires"}}}],"z":5,"attrs":{"line":{"stroke":"red"}}},{"type":"basic.Image","position":{"x":400,"y":350},"size":{"width":100,"height":100},"angle":0,"id":"4","z":6,"attrs":{"text":{"text":"Product Listing","display":"","stroke":"#000000"},"image":{"xlink:href":"../../assets/Images/window.jpg","width":100,"height":100}}},{"type":"standard.Link","source":{"id":"2","port":"out"},"target":{"id":"4","port":"in"},"id":"bf53b199-b3eb-430f-9c91-39353e1db483","labels":[{"attrs":{"text":{"text":"Requires"}}}],"z":7,"attrs":{"line":{"stroke":"red"}}},{"type":"basic.Image","position":{"x":650,"y":350},"size":{"width":100,"height":100},"angle":0,"id":"5","z":8,"attrs":{"text":{"text":"Web store","display":"","stroke":"#000000"},"image":{"xlink:href":"../../assets/Images/window.jpg","width":100,"height":100}}},{"type":"standard.Link","source":{"id":"2","port":"out"},"target":{"id":"5","port":"in"},"id":"bccdc73a-8579-4b1d-b1f8-832c9a673fef","labels":[{"attrs":{"text":{"text":"Requires"}}}],"z":9,"attrs":{"line":{"stroke":"red"}}},{"type":"standard.Link","source":{"id":"5","port":"out"},"target":{"id":"6","port":"in"},"id":"72a64c3d-771a-4a8f-83db-240f71a7d799","labels":[{"attrs":{"text":{"text":"Requires"}}}],"z":10,"attrs":{"line":{"stroke":"red"}}},{"type":"standard.Link","source":{"id":"5","port":"out"},"target":{"id":"7","port":"in"},"id":"e1b7b281-b1e0-4773-97f9-6a89f53ee8d1","labels":[{"attrs":{"text":{"text":"Requires"}}}],"z":11,"attrs":{"line":{"stroke":"red"}}},{"type":"standard.Link","source":{"id":"5","port":"out"},"target":{"id":"8","port":"in"},"id":"ead97d64-3239-41a1-9689-44f3e76e38fb","labels":[{"attrs":{"text":{"text":"Requires"}}}],"z":12,"attrs":{"line":{"stroke":"red"}}},{"type":"basic.Image","position":{"x":870,"y":150},"size":{"width":100,"height":100},"angle":0,"id":"6","z":13,"attrs":{"text":{"text":"pwds1","display":"","stroke":"#000000"},"image":{"xlink:href":"../../assets/Images/computer.jpg","width":100,"height":100}}},{"type":"basic.Image","position":{"x":870,"y":350},"size":{"width":100,"height":100},"angle":0,"id":"7","z":14,"attrs":{"text":{"text":"pwds2","display":"","stroke":"#000000"},"image":{"xlink:href":"../../assets/Images/computer.jpg","width":100,"height":100}}},{"type":"standard.BorderedImage","position":{"x":870,"y":550},"size":{"width":100,"height":100},"angle":0,"id":"8","z":15,"attrs":{"image":{"xlink:href":"../../assets/Images/computer.jpg","width":100,"height":100},"label":{"text":"pwedsr0Main"}}},{"type":"standard.BorderedImage","position":{"x":650,"y":600},"size":{"width":100,"height":100},"angle":0,"id":"9","z":16,"attrs":{"image":{"xlink:href":"../../assets/Images/customer.jpg","width":100,"height":100},"label":{"text":" Customer"}}},{"type":"standard.Link","source":{"id":"9","port":"out"},"target":{"id":"5","port":"in"},"id":"81dc0f4e-0210-423b-9420-ceb311c48d3a","labels":[{"attrs":{"text":{"text":"Serves To"}}}],"z":17,"attrs":{"line":{"stroke":"yellow"}}}]}
